MANIFEST.in
RELEASE-VERSION
pavement.py
paver-minilib.zip
setup.py
version.py
pandas_helpers/__init__.py
pandas_helpers.egg-info/PKG-INFO
pandas_helpers.egg-info/SOURCES.txt
pandas_helpers.egg-info/dependency_links.txt
pandas_helpers.egg-info/requires.txt
pandas_helpers.egg-info/top_level.txt