Metadata-Version: 1.0
Name: pandas-helpers
Version: 0.1
Summary: Helper functions for working with pandas
Home-page: http://github.com/wheeler-microfluidics/pandas-helpers.git
Author: Ryan Fobel
Author-email: ryan@fobel.net
License: GPLv2
Platform: UNKNOWN
